[  
   {  
      "FileName":"About_To_Pounce_Final_v3_1_of_1.jpg",
      "Make":"NIKON CORPORATION",
      "Model":"NIKON D7000",
      "ExposureProgram":"Aperture-priority AE",
      "ISO":320,
      "CreateDate":"2013:11:04 20:21:46",
      "FocalLength":"35.0 mm",
      "Aperture":4.5,
      "ImageSize":"2644x2504",
      "ShutterSpeed":"1/60",
      "Category":"Composite",
      "IsGetty":false,
      "IsHDR":false,
      "IsBW":false,
      "pjRank":100
   },
   {  
      "FileName":"As_the_crow_flies_Final1_of_1.jpg",
      "Model":"NIKON D7000",
      "ISO":100,
      "FocalLength":"40.0 mm",
      "CreateDate":"2014:03:21 18:38:30",
      "Aperture":6.3,
      "ImageSize":"5469x3071",
      "ShutterSpeed":"1/125",
      "Category":"Composite",
      "IsGetty":false,
      "IsHDR":false,
      "IsBW":false,
      "pjRank":100
   },
   {  
      "FileName":"BMXJump.jpg",
      "Model":"NIKON D7000",
      "ISO":100,
      "FocalLength":"75.0 mm",
      "CreateDate":"2013:05:11 14:55:39",
      "Aperture":7.1,
      "ImageSize":"4792x3054",
      "ShutterSpeed":"1/800",
      "Category":"Composite",
      "IsGetty":false,
      "IsHDR":false,
      "IsBW":false,
      "pjRank":100
   },
   {  
      "FileName":"Book_Throw_Final_1_of_1.jpg",
      "Model":"NIKON D7000",
      "ISO":100,
      "FocalLength":"75.0 mm",
      "CreateDate":"2013:05:11 14:55:39",
      "Aperture":7.1,
      "ImageSize":"5048x3565",
      "Category":"Composite",
      "IsGetty":false,
      "IsHDR":false,
      "IsBW":false,
      "pjRank":100
   },
   {  
      "FileName":"CaravanSitePlayWIPFlattenedv1finalv3altcropForUpload.jpg",
      "Make":"samsung",
      "Model":"SM-G903F",
      "ISO":40,
      "CreateDate":"2016:08:14 08:36:12",
      "FocalLength":"3.7 mm",
      "Aperture":1.9,
      "ImageSize":"1992x1121",
      "ShutterSpeed":"1/602",
      "Category":"Composite",
      "IsGetty":false,
      "IsHDR":false,
      "IsBW":false,
      "pjRank":100
   },
   {  
      "FileName":"Church_Final2.jpg",
      "Make":"NIKON CORPORATION",
      "Model":"NIKON D7000",
      "ExposureProgram":"Aperture-priority AE",
      "ISO":100,
      "CreateDate":"2013:12:13 13:36:13",
      "FocalLength":"18.0 mm",
      "Aperture":16.0,
      "ImageSize":"4659x3433",
      "ShutterSpeed":"1/13",
      "Category":"Composite",
      "IsGetty":false,
      "IsHDR":false,
      "IsBW":false,
      "pjRank":100
   },
   {  
      "FileName":"Cloud_City_Final_21_of_1.jpg",
      "Make":"NIKON CORPORATION",
      "Model":"NIKON D7000",
      "ExposureProgram":"Aperture-priority AE",
      "ISO":100,
      "CreateDate":"2014:03:05 08:01:34",
      "FocalLength":"25.0 mm",
      "Aperture":16.0,
      "ImageSize":"5847x2969",
      "ShutterSpeed":"1/6",
      "Category":"Composite",
      "IsGetty":false,
      "IsHDR":false,
      "IsBW":false,
      "pjRank":100
   },
   {  
      "FileName":"CreepyWoodsFinal_v2.3_1_of_1.jpg",
      "Make":"NIKON CORPORATION",
      "Model":"NIKON D7000",
      "ExposureProgram":"Aperture-priority AE",
      "ISO":100,
      "CreateDate":"2015:04:08 07:42:14",
      "FocalLength":"18.0 mm",
      "Aperture":16.0,
      "ImageSize":"4731x3242",
      "ShutterSpeed":"1/15",
      "Category":"Composite",
      "IsGetty":false,
      "IsHDR":false,
      "IsBW":false,
      "pjRank":100
   },
   {  
      "FileName":"Delivery_Final_v11_of_1.jpg",
      "Model":"NIKON D7000",
      "ISO":100,
      "FocalLength":"18.0 mm",
      "CreateDate":"2014:08:27 07:30:44",
      "Aperture":16.0,
      "ImageSize":"5368x3353",
      "ShutterSpeed":"1/4",
      "Category":"Composite",
      "IsGetty":false,
      "IsHDR":false,
      "IsBW":false,
      "pjRank":100
   },
   {  
      "FileName":"Driving_To_Work_Final_Maybe_1_of_1.jpg",
      "Model":"NIKON D7000",
      "ISO":100,
      "FocalLength":"40.0 mm",
      "CreateDate":"2013:07:26 06:29:48",
      "Aperture":16.0,
      "ImageSize":"3002x3114",
      "ShutterSpeed":"1/80",
      "Category":"Composite",
      "IsGetty":false,
      "IsHDR":false,
      "IsBW":false,
      "pjRank":100
   },
   {  
      "FileName":"Empty_M6_Prject_with_emiratesv2final1_of_1.jpg",
      "Make":"NIKON CORPORATION",
      "Model":"NIKON D7000",
      "ISO":200,
      "CreateDate":"2013:05:04 11:59:50",
      "FocalLength":"18.0 mm",
      "Aperture":22.0,
      "ImageSize":"2011x983",
      "ShutterSpeed":25,
      "Category":"Composite",
      "IsGetty":false,
      "IsHDR":false,
      "IsBW":false,
      "pjRank":100
   },
   {  
      "FileName":"Flying_High_6_1_of_1.jpg",
      "Make":"NIKON CORPORATION",
      "Model":"NIKON D7000",
      "ISO":200,
      "CreateDate":"2013:05:04 11:59:50",
      "FocalLength":"18.0 mm",
      "Aperture":22.0,
      "CreateDate":"2012:07:04 22:33:03",
      "ImageSize":"4772x3077",
      "Category":"Composite",
      "IsGetty":false,
      "IsHDR":false,
      "IsBW":false,
      "pjRank":100
   },
   {  
      "FileName":"Fly_Me_to_the_Moon_v2_1_of_1.jpg",
      "Make":"NIKON CORPORATION",
      "Model":"NIKON D7000",
      "ISO":100,
      "CreateDate":"2015:02:05 22:05:19",
      "FocalLength":"300.0 mm",
      "Aperture":16.0,
      "ImageSize":"2138x2138",
      "ShutterSpeed":"1/5",
      "Category":"Composite",
      "IsGetty":false,
      "IsHDR":false,
      "IsBW":false,
      "pjRank":100
   },
   {  
      "FileName":"Halloween2014Finalv1.jpg",
      "Make":"NIKON CORPORATION",
      "Model":"NIKON D7000",
      "ExposureProgram":"Aperture-priority AE",
      "ISO":100,
      "CreateDate":"2014:01:11 15:15:59",
      "FocalLength":"18.0 mm",
      "Aperture":16.0,
      "ImageSize":"4320x3108",
      "ShutterSpeed":"1/640",
      "Category":"Composite",
      "IsGetty":false,
      "IsHDR":false,
      "IsBW":false,
      "pjRank":100
   },
   {  
      "FileName":"Heavens_Open_Final_1_of_1.jpg",
      "Make":"NIKON CORPORATION",
      "Model":"NIKON D7000",
      "ExposureProgram":"Aperture-priority AE",
      "ISO":100,
      "CreateDate":"2014:03:21 18:38:08",
      "FocalLength":"105.0 mm",
      "Aperture":6.3,
      "ImageSize":"5226x3351",
      "ShutterSpeed":"1/1250",
      "Category":"Composite",
      "IsGetty":false,
      "IsHDR":false,
      "IsBW":false,
      "pjRank":100
   },
   {  
      "FileName":"If_You_Go_Down_To_The_Woods_Today_1_of_1_Finalv2.6.jpg",
      "Model":"NIKON D7000",
      "ISO":100,
      "FocalLength":"18.0 mm",
      "CreateDate":"2015:01:04 12:27:15",
      "Aperture":16.0,
      "ImageSize":"1869x1018",
      "ShutterSpeed":"1/50",
      "Category":"Composite",
      "IsGetty":false,
      "IsHDR":false,
      "IsBW":false,
      "pjRank":100
   },
   {  
      "FileName":"In_A_World_Of_Make_Believe_2.jpg",
      "Make":"NIKON CORPORATION",
      "Model":"NIKON D7000",
      "ExposureProgram":"Aperture-priority AE",
      "ISO":100,
      "CreateDate":"2013:12:05 18:43:21",
      "FocalLength":"30.0 mm",
      "SlicesGroupName":"In A World Of Make Believe",
      "Aperture":16.0,
      "ImageSize":"5799x3103",
      "ShutterSpeed":30,
      "Category":"Composite",
      "IsGetty":false,
      "IsHDR":false,
      "IsBW":false,
      "pjRank":100
   },
   {  
      "FileName":"I_Want_To_Break_Free.jpg",
      "Model":"NIKON D7000",
      "ISO":100,
      "FocalLength":"75.0 mm",
      "CreateDate":"2013:05:11 14:55:39",
      "Aperture":7.1,
      "ImageSize":"7881x4696",
      "ShutterSpeed":"1/800",
      "Category":"Composite",
      "IsGetty":false,
      "IsHDR":false,
      "IsBW":false,
      "pjRank":100
   },
   {  
      "FileName":"Kerpow3_with_explosion_v3_1_of_1.jpg",
      "Make":"NIKON CORPORATION",
      "Model":"NIKON D7000",
      "ExposureProgram":"Aperture-priority AE",
      "ISO":640,
      "CreateDate":"2016:02:27 16:44:11",
      "FocalLength":"18.0 mm",
      "Aperture":6.3,
      "ImageSize":"3192x4840",
      "ShutterSpeed":"1/250",
      "Category":"Composite",
      "IsGetty":false,
      "IsHDR":false,
      "IsBW":false,
      "pjRank":100
   },
   {  
      "FileName":"LIghts_Will_Guide_You_V3.jpg",
      "Model":"NIKON D7000",
      "ISO":100,
      "CreateDate":"2012:11:11 18:35:49",
      "FocalLength":"18.0 mm",
      "Aperture":16.0,
      "ImageSize":"5545x2885",
      "ShutterSpeed":10,
      "Category":"Composite",
      "IsGetty":false,
      "IsHDR":false,
      "IsBW":false,
      "pjRank":100
   },
   {  
      "FileName":"Lost_In_Technology_Final_1_of_1.jpg",
      "Make":"NIKON CORPORATION",
      "Model":"NIKON D7000",
      "ExposureProgram":"Aperture-priority AE",
      "ISO":250,
      "CreateDate":"2015:05:25 09:35:49",
      "FocalLength":"100.0 mm",
      "Aperture":20.0,
      "ImageSize":"5179x2940",
      "ShutterSpeed":0.6,
      "Category":"Composite",
      "IsGetty":false,
      "IsHDR":false,
      "IsBW":false,
      "pjRank":100
   },
   {  
      "FileName":"M6_Light_Trails_V2_With_Moon_1_of_1.jpg",
      "Make":"NIKON CORPORATION",
      "Model":"NIKON D7000",
      "ISO":160,
      "CreateDate":"2013:09:23 20:08:17",
      "FocalLength":"18.0 mm",
      "Aperture":16.0,
      "ImageSize":"4827x3197",
      "ShutterSpeed":76,
      "Category":"Composite",
      "IsGetty":false,
      "IsHDR":false,
      "IsBW":false,
      "pjRank":100
   },
   {  
      "FileName":"Merry_Christmas_2013__V3.jpg",
      "Model":"NIKON D7000",
      "ISO":100,
      "FocalLength":"18.0 mm",
      "CreateDate":"2013:01:26 13:00:22",
      "Aperture":16.0,
      "ImageSize":"4867x3286",
      "ShutterSpeed":"1/60",
      "Category":"Composite",
      "IsGetty":false,
      "IsHDR":false,
      "IsBW":false,
      "pjRank":100
   },
   {  
      "FileName":"Merry_Christmas_Fina_v2l.jpg",
      "Make":"NIKON CORPORATION",
      "Model":"NIKON D7000",
      "ISO":200,
      "CreateDate":"2013:12:24 17:14:53",
      "FocalLength":"50.0 mm",
      "Aperture":3.2,
      "ImageSize":"4780x3346",
      "ShutterSpeed":1.3,
      "Category":"Composite",
      "IsGetty":false,
      "IsHDR":false,
      "IsBW":false,
      "pjRank":100
   },
   {  
      "FileName":"MoonLightStMary.jpg",
      "Model":"NIKON D7000",
      "ISO":100,
      "FocalLength":"18.0 mm",
      "CreateDate":"2013:02:23 16:15:40",
      "Aperture":16.0,
      "ImageSize":"4913x3256",
      "ShutterSpeed":"1/20",
      "Category":"Composite",
      "IsGetty":false,
      "IsHDR":false,
      "IsBW":false,
      "pjRank":100
   },
   {  
      "FileName":"Moonlit_Walkjpg.jpg",
      "Make":"NIKON CORPORATION",
      "Model":"NIKON D7000",
      "ExposureProgram":"Aperture-priority AE",
      "ISO":100,
      "CreateDate":"2014:01:11 15:15:59",
      "FocalLength":"18.0 mm",
      "Aperture":16.0,
      "ImageSize":"2020x1322",
      "ShutterSpeed":"1/640",
      "Category":"Composite",
      "IsGetty":false,
      "IsHDR":false,
      "IsBW":false,
      "pjRank":100
   },
   {  
      "FileName":"Oli_and_Alfi_1_of_1.jpg",
      "Make":"NIKON CORPORATION",
      "Model":"NIKON D7000",
      "ExposureProgram":"Aperture-priority AE",
      "ISO":640,
      "CreateDate":"2012:06:30 09:47:11",
      "FocalLength":"105.0 mm",
      "Aperture":7.1,
      "ImageSize":"4407x2907",
      "ShutterSpeed":"1/1250",
      "Category":"Composite",
      "IsGetty":false,
      "IsHDR":false,
      "IsBW":false,
      "pjRank":100
   },
   {  
      "FileName":"Piano_Run_Final_1_of_1.jpg",
      "Make":"NIKON CORPORATION",
      "Model":"NIKON D7000",
      "ExposureProgram":"Aperture-priority AE",
      "ISO":500,
      "CreateDate":"2014:05:10 15:49:12",
      "FocalLength":"50.0 mm",
      "Aperture":1.8,
      "ImageSize":"3533x3339",
      "ShutterSpeed":"1/640",
      "Category":"Composite",
      "IsGetty":false,
      "IsHDR":false,
      "IsBW":false,
      "pjRank":100
   },
   {  
      "FileName":"Reach_For_The_Sky_V4_Final1_of_1.jpg",
      "Model":"NIKON D7000",
      "ISO":100,
      "FocalLength":"18.0 mm",
      "CreateDate":"2012:10:01 18:28:00",
      "Aperture":16.0,
      "ImageSize":"4574x3061",
      "ShutterSpeed":"1/10",
      "Category":"Composite",
      "IsGetty":false,
      "IsHDR":false,
      "IsBW":false,
      "pjRank":100
   },
   {  
      "FileName":"Run_Away!!_Infrared_V21_of_1.jpg",
      "Model":"NIKON D7000",
      "ISO":100,
      "FocalLength":"18.0 mm",
      "CreateDate":"2012:10:27 13:48:56",
      "Aperture":16.0,
      "ImageSize":"4943x3278",
      "ShutterSpeed":"1/50",
      "Category":"Composite",
      "IsGetty":false,
      "IsHDR":false,
      "IsBW":false,
      "pjRank":100
   },
   {  
      "FileName":"SailingAwayVersion3_1_of_1.jpg",
      "Make":"NIKON CORPORATION",
      "Model":"NIKON D7000",
      "ExposureProgram":"Aperture-priority AE",
      "ISO":100,
      "CreateDate":"2014:03:21 18:38:08",
      "FocalLength":"105.0 mm",
      "Aperture":6.3,
      "ImageSize":"4712x2970",
      "ShutterSpeed":"1/1250",
      "Category":"Composite",
      "IsGetty":false,
      "IsHDR":false,
      "IsBW":false,
      "pjRank":100
   },
   {  
      "FileName":"The_Art_of_Levitation_getty.jpg",
      "Model":"NIKON D7000",
      "ISO":100,
      "FocalLength":"18.0 mm",
      "CreateDate":"2014:02:02 14:15:27",
      "Aperture":16.0,
      "ImageSize":"5188x3171",
      "ShutterSpeed":"1/60",
      "Category":"Composite",
      "IsGetty":false,
      "IsHDR":false,
      "IsBW":false,
      "pjRank":100
   },
   {  
      "FileName":"TheCoffeeCupFinal.jpg",
      "Make":"SAMSUNG",
      "Model":"GT-I9300",
      "ExposureProgram":"Aperture-priority AE",
      "ISO":80,
      "CreateDate":"2015:03:29 15:40:30",
      "FocalLength":"3.7 mm",
      "Aperture":2.6,
      "ImageSize":"3264x2448",
      "ShutterSpeed":"1/100",
      "Category":"Composite",
      "IsGetty":false,
      "IsHDR":false,
      "IsBW":false,
      "pjRank":100
   },
   {  
      "FileName":"The_Distorted_Forest_Final_V5_Figure_Added_With_Flare_Flipped.jpg",
      "Make":"NIKON CORPORATION",
      "Model":"NIKON D7000",
      "ExposureProgram":"Aperture-priority AE",
      "ISO":100,
      "CreateDate":"2014:01:03 13:38:30",
      "FocalLength":"48.0 mm",
      "Aperture":16.0,
      "ImageSize":"4985x3209",
      "ShutterSpeed":"1/4",
      "Category":"Composite",
      "IsGetty":false,
      "IsHDR":false,
      "IsBW":false,
      "pjRank":100
   },
   {  
      "FileName":"The_Evil_Eye_Of_The_Storm_Version_3_1_of_1.jpg",
      "Model":"NIKON D7000",
      "ISO":100,
      "CreateDate":"2013:04:29 11:25:50",
      "FocalLength":"18.0 mm",
      "Aperture":16.0,
      "ImageSize":"4279x2821",
      "ShutterSpeed":"1/80",
      "Category":"Composite",
      "IsGetty":false,
      "IsHDR":false,
      "IsBW":false,
      "pjRank":100
   },
   {  
      "FileName":"The_Ghost_Of_Delamere_Final_1_of_1.jpg",
      "Make":"NIKON CORPORATION",
      "Model":"NIKON D7000",
      "ISO":320,
      "CreateDate":"2014:10:19 11:18:11",
      "FocalLength":"18.0 mm",
      "Aperture":18.0,
      "ImageSize":"5213x3453",
      "ShutterSpeed":20,
      "Category":"Composite",
      "IsGetty":false,
      "IsHDR":false,
      "IsBW":false,
      "pjRank":100
   },
   {  
      "FileName":"The_Great_Escape_Final_Final_1_of_1.jpg",
      "Model":"NIKON D7000",
      "ISO":100,
      "CreateDate":"2013:10:29 17:13:24",
      "FocalLength":"18.0 mm",
      "Aperture":16.0,
      "ImageSize":"4205x2969",
      "ShutterSpeed":"1/13",
      "Category":"Composite",
      "IsGetty":false,
      "IsHDR":false,
      "IsBW":false,
      "pjRank":100
   },
   {  
      "FileName":"TheMagicOfTheSeaside._Final.jpg",
      "Model":"NIKON D7000",
      "ISO":100,
      "FocalLength":"18.0 mm",
      "CreateDate":"2014:02:21 15:28:50",
      "Aperture":8.0,
      "ImageSize":"5492x3641",
      "ShutterSpeed":"1/250",
      "Category":"Composite",
      "IsGetty":false,
      "IsHDR":false,
      "IsBW":false,
      "pjRank":100
   },
   {  
      "FileName":"TreadCarefully-Finalv3.jpg",
      "Make":"NIKON CORPORATION",
      "Model":"NIKON D7000",
      "ExposureProgram":"Aperture-priority AE",
      "ISO":320,
      "CreateDate":"2013:04:06 11:01:41",
      "FocalLength":"70.0 mm",
      "Aperture":4.5,
      "ImageSize":"4920x3150",
      "ShutterSpeed":"1/800",
      "Category":"Composite",
      "IsGetty":false,
      "IsHDR":false,
      "IsBW":false,
      "pjRank":100
   }
]
